{"nodes": [{"id": "src_components_recipe_scattered_paws_tsx", "label": "scattered-paws.tsx", "file_type": "code", "source_file": "src/components/recipe/scattered-paws.tsx", "source_location": "L1"}, {"id": "scattered_paws_scatteredpaws", "label": "ScatteredPaws()", "file_type": "code", "source_file": "src/components/recipe/scattered-paws.tsx", "source_location": "L26"}], "edges": [{"source": "src_components_recipe_scattered_paws_tsx", "target": "scattered_paws_scatteredpaws", "relation": "contains", "confidence": "EXTRACTED", "source_file": "src/components/recipe/scattered-paws.tsx", "source_location": "L26", "weight": 1.0}]}